{"frames": {

"active_antidot.png":
{
	"frame": {"x":227,"y":209,"w":23,"h":23},
	"rotated": false,
	"trimmed": false,
	"spriteSourceSize": {"x":0,"y":0,"w":23,"h":23},
	"sourceSize": {"w":23,"h":23}
},
"active_dot.png":
{
	"frame": {"x":289,"y":1,"w":22,"h":22},
	"rotated": false,
	"trimmed": false,
	"spriteSourceSize": {"x":0,"y":0,"w":22,"h":22},
	"sourceSize": {"w":22,"h":22}
},
"antidot_div_value.png":
{
	"frame": {"x":163,"y":209,"w":30,"h":37},
	"rotated": false,
	"trimmed": false,
	"spriteSourceSize": {"x":0,"y":0,"w":30,"h":37},
	"sourceSize": {"w":30,"h":37}
},
"antidot_value.png":
{
	"frame": {"x":163,"y":1,"w":124,"h":102},
	"rotated": false,
	"trimmed": true,
	"spriteSourceSize": {"x":13,"y":12,"w":124,"h":102},
	"sourceSize": {"w":151,"h":126}
},
"blue_antidot.png":
{
	"frame": {"x":289,"y":25,"w":22,"h":22},
	"rotated": false,
	"trimmed": false,
	"spriteSourceSize": {"x":0,"y":0,"w":22,"h":22},
	"sourceSize": {"w":22,"h":22}
},
"blue_dot.png":
{
	"frame": {"x":289,"y":97,"w":20,"h":20},
	"rotated": false,
	"trimmed": false,
	"spriteSourceSize": {"x":0,"y":0,"w":20,"h":20},
	"sourceSize": {"w":20,"h":20}
},
"box.png":
{
	"frame": {"x":1,"y":1,"w":160,"h":242},
	"rotated": false,
	"trimmed": false,
	"spriteSourceSize": {"x":0,"y":0,"w":160,"h":242},
	"sourceSize": {"w":160,"h":242}
},
"dot_div_value.png":
{
	"frame": {"x":195,"y":209,"w":30,"h":37},
	"rotated": false,
	"trimmed": false,
	"spriteSourceSize": {"x":0,"y":0,"w":30,"h":37},
	"sourceSize": {"w":30,"h":37}
},
"dot_value.png":
{
	"frame": {"x":163,"y":105,"w":124,"h":102},
	"rotated": false,
	"trimmed": true,
	"spriteSourceSize": {"x":13,"y":12,"w":124,"h":102},
	"sourceSize": {"w":151,"h":126}
},
"inactive_antidot.png":
{
	"frame": {"x":289,"y":49,"w":22,"h":22},
	"rotated": false,
	"trimmed": false,
	"spriteSourceSize": {"x":0,"y":0,"w":22,"h":22},
	"sourceSize": {"w":22,"h":22}
},
"inactive_dot.png":
{
	"frame": {"x":289,"y":119,"w":20,"h":20},
	"rotated": false,
	"trimmed": false,
	"spriteSourceSize": {"x":0,"y":0,"w":20,"h":20},
	"sourceSize": {"w":20,"h":20}
},
"red_antidot.png":
{
	"frame": {"x":289,"y":73,"w":22,"h":22},
	"rotated": false,
	"trimmed": false,
	"spriteSourceSize": {"x":0,"y":0,"w":22,"h":22},
	"sourceSize": {"w":22,"h":22}
},
"red_dot.png":
{
	"frame": {"x":289,"y":141,"w":20,"h":20},
	"rotated": false,
	"trimmed": false,
	"spriteSourceSize": {"x":0,"y":0,"w":20,"h":20},
	"sourceSize": {"w":20,"h":20}
},
"separator.png":
{
	"frame": {"x":1,"y":245,"w":153,"h":1},
	"rotated": false,
	"trimmed": false,
	"spriteSourceSize": {"x":0,"y":0,"w":153,"h":1},
	"sourceSize": {"w":153,"h":1}
}},
"meta": {
	"app": "http://www.codeandweb.com/texturepacker",
	"version": "1.0",
	"image": "machine@1x.png",
	"format": "RGBA8888",
	"size": {"w":312,"h":247},
	"scale": "0.25",
	"smartupdate": "$TexturePacker:SmartUpdate:20382514b63b24828163bfabc677922a:f89074a9c6da1217d85adbee7a95d4b7:4796a15fbc349289e0bf0ffff273cc77$"
}
}
